[
    {
        "crashpoint": 21.392752,
        "startTime": "2025-03-23T21:19:43",
        "records_since_previous": 4,
        "time_since_previous": "0:02:18"
    },
    {
        "crashpoint": 67.03879,
        "startTime": "2025-03-23T21:17:25",
        "records_since_previous": 22,
        "time_since_previous": "0:10:51"
    },
    {
        "crashpoint": 34.253105,
        "startTime": "2025-03-23T21:06:34",
        "records_since_previous": 49,
        "time_since_previous": "0:44:53"
    },
    {
        "crashpoint": 33.38,
        "startTime": "2025-03-23T20:21:41",
        "records_since_previous": 7,
        "time_since_previous": "0:03:53"
    },
    {
        "crashpoint": 19.48,
        "startTime": "2025-03-23T20:17:48",
        "records_since_previous": 20,
        "time_since_previous": "0:10:18"
    },
    {
        "crashpoint": 14070.54,
        "startTime": "2025-03-23T20:07:30",
        "records_since_previous": 24,
        "time_since_previous": "0:11:58"
    },
    {
        "crashpoint": 20.74,
        "startTime": "2025-03-23T19:55:32",
        "records_since_previous": 18,
        "time_since_previous": "0:09:44"
    },
    {
        "crashpoint": 31.43,
        "startTime": "2025-03-23T19:45:48",
        "records_since_previous": 8,
        "time_since_previous": "0:05:09"
    },
    {
        "crashpoint": 44.0,
        "startTime": "2025-03-23T19:40:39",
        "records_since_previous": 5,
        "time_since_previous": "0:03:29"
    },
    {
        "crashpoint": 21.61,
        "startTime": "2025-03-23T19:37:10",
        "records_since_previous": 10,
        "time_since_previous": "0:04:31"
    },
    {
        "crashpoint": 28.81,
        "startTime": "2025-03-23T19:32:39",
        "records_since_previous": 2,
        "time_since_previous": "0:02:18"
    },
    {
        "crashpoint": 264.51,
        "startTime": "2025-03-23T19:30:21",
        "records_since_previous": 42,
        "time_since_previous": "0:18:43"
    },
    {
        "crashpoint": 50.58,
        "startTime": "2025-03-23T19:11:38",
        "records_since_previous": 61,
        "time_since_previous": "0:26:30"
    },
    {
        "crashpoint": 46.88,
        "startTime": "2025-03-23T18:45:08",
        "records_since_previous": 10,
        "time_since_previous": "0:05:32"
    },
    {
        "crashpoint": 22.7,
        "startTime": "2025-03-23T18:39:36",
        "records_since_previous": 30,
        "time_since_previous": "0:14:11"
    },
    {
        "crashpoint": 23.93,
        "startTime": "2025-03-23T18:25:25",
        "records_since_previous": 34,
        "time_since_previous": "0:16:00"
    },
    {
        "crashpoint": 43.37,
        "startTime": "2025-03-23T18:09:25",
        "records_since_previous": 10,
        "time_since_previous": "0:05:36"
    },
    {
        "crashpoint": 100.92,
        "startTime": "2025-03-23T18:03:49",
        "records_since_previous": 65,
        "time_since_previous": "0:28:41"
    },
    {
        "crashpoint": 43.33,
        "startTime": "2025-03-23T17:35:08",
        "records_since_previous": 24,
        "time_since_previous": "0:11:08"
    },
    {
        "crashpoint": 54.73,
        "startTime": "2025-03-23T17:24:00",
        "records_since_previous": 41,
        "time_since_previous": "0:20:30"
    },
    {
        "crashpoint": 142.24,
        "startTime": "2025-03-23T17:03:30",
        "records_since_previous": 9,
        "time_since_previous": "0:04:47"
    },
    {
        "crashpoint": 43.71,
        "startTime": "2025-03-23T16:58:43",
        "records_since_previous": 17,
        "time_since_previous": "0:07:21"
    },
    {
        "crashpoint": 53.09,
        "startTime": "2025-03-23T16:51:22",
        "records_since_previous": 41,
        "time_since_previous": "0:18:37"
    },
    {
        "crashpoint": 53.8,
        "startTime": "2025-03-23T16:32:45",
        "records_since_previous": 2,
        "time_since_previous": "0:02:32"
    },
    {
        "crashpoint": 896.1,
        "startTime": "2025-03-23T16:30:13",
        "records_since_previous": 20,
        "time_since_previous": "0:08:03"
    },
    {
        "crashpoint": 42.15,
        "startTime": "2025-03-23T16:22:10",
        "records_since_previous": 22,
        "time_since_previous": "0:10:29"
    },
    {
        "crashpoint": 21.62,
        "startTime": "2025-03-23T16:11:41",
        "records_since_previous": 5,
        "time_since_previous": "0:02:05"
    },
    {
        "crashpoint": 21.4,
        "startTime": "2025-03-23T16:09:36",
        "records_since_previous": 10,
        "time_since_previous": "0:05:09"
    },
    {
        "crashpoint": 31.04,
        "startTime": "2025-03-23T16:04:27",
        "records_since_previous": 25,
        "time_since_previous": "0:11:15"
    },
    {
        "crashpoint": 23.75,
        "startTime": "2025-03-23T15:53:12",
        "records_since_previous": 51,
        "time_since_previous": "0:21:39"
    },
    {
        "crashpoint": 47.47,
        "startTime": "2025-03-23T15:31:33",
        "records_since_previous": 22,
        "time_since_previous": "0:10:55"
    },
    {
        "crashpoint": 22.08,
        "startTime": "2025-03-23T15:20:38",
        "records_since_previous": 26,
        "time_since_previous": "0:13:11"
    },
    {
        "crashpoint": 338.1,
        "startTime": "2025-03-23T15:07:27",
        "records_since_previous": 5,
        "time_since_previous": "0:02:39"
    },
    {
        "crashpoint": 31.18,
        "startTime": "2025-03-23T15:04:48",
        "records_since_previous": 9,
        "time_since_previous": "0:03:57"
    },
    {
        "crashpoint": 24.11,
        "startTime": "2025-03-23T15:00:51",
        "records_since_previous": 5,
        "time_since_previous": "0:03:20"
    },
    {
        "crashpoint": 24.19,
        "startTime": "2025-03-23T14:57:31",
        "records_since_previous": 4,
        "time_since_previous": "0:02:00"
    },
    {
        "crashpoint": 25.28,
        "startTime": "2025-03-23T14:55:31",
        "records_since_previous": 59,
        "time_since_previous": "0:25:55"
    },
    {
        "crashpoint": 23.46,
        "startTime": "2025-03-23T14:29:36",
        "records_since_previous": 38,
        "time_since_previous": "0:17:33"
    },
    {
        "crashpoint": 42.84,
        "startTime": "2025-03-23T14:12:03",
        "records_since_previous": 15,
        "time_since_previous": "0:06:45"
    },
    {
        "crashpoint": 559.96,
        "startTime": "2025-03-23T14:05:18",
        "records_since_previous": 24,
        "time_since_previous": "0:11:45"
    },
    {
        "crashpoint": 78.67,
        "startTime": "2025-03-23T13:53:33",
        "records_since_previous": 13,
        "time_since_previous": "0:06:07"
    },
    {
        "crashpoint": 228.29,
        "startTime": "2025-03-23T13:47:26",
        "records_since_previous": 7,
        "time_since_previous": "0:03:58"
    },
    {
        "crashpoint": 23.68,
        "startTime": "2025-03-23T13:43:28",
        "records_since_previous": 6,
        "time_since_previous": "0:03:44"
    },
    {
        "crashpoint": 375.02,
        "startTime": "2025-03-23T13:39:44",
        "records_since_previous": 7,
        "time_since_previous": "0:03:22"
    },
    {
        "crashpoint": 23.12,
        "startTime": "2025-03-23T13:36:22",
        "records_since_previous": 6,
        "time_since_previous": "0:04:43"
    },
    {
        "crashpoint": 694.69,
        "startTime": "2025-03-23T13:31:39",
        "records_since_previous": 49,
        "time_since_previous": "0:24:04"
    },
    {
        "crashpoint": 409.7,
        "startTime": "2025-03-23T13:07:35",
        "records_since_previous": 15,
        "time_since_previous": "0:07:40"
    },
    {
        "crashpoint": 317.97,
        "startTime": "2025-03-23T12:59:55",
        "records_since_previous": 49,
        "time_since_previous": "0:22:46"
    },
    {
        "crashpoint": 146.64,
        "startTime": "2025-03-23T12:37:09",
        "records_since_previous": 20,
        "time_since_previous": "0:09:10"
    },
    {
        "crashpoint": 176.69,
        "startTime": "2025-03-23T12:27:59",
        "records_since_previous": 3,
        "time_since_previous": "0:01:57"
    },
    {
        "crashpoint": 41.4,
        "startTime": "2025-03-23T12:26:02",
        "records_since_previous": 28,
        "time_since_previous": "0:11:47"
    },
    {
        "crashpoint": 157.27,
        "startTime": "2025-03-23T12:14:15",
        "records_since_previous": 18,
        "time_since_previous": "0:08:10"
    },
    {
        "crashpoint": 28.16,
        "startTime": "2025-03-23T12:06:05",
        "records_since_previous": 20,
        "time_since_previous": "0:10:01"
    },
    {
        "crashpoint": 195.1,
        "startTime": "2025-03-23T11:56:04",
        "records_since_previous": 26,
        "time_since_previous": "0:14:57"
    },
    {
        "crashpoint": 140.03,
        "startTime": "2025-03-23T11:41:07",
        "records_since_previous": 39,
        "time_since_previous": "0:18:52"
    },
    {
        "crashpoint": 108.78,
        "startTime": "2025-03-23T11:22:15",
        "records_since_previous": 19,
        "time_since_previous": "0:08:01"
    },
    {
        "crashpoint": 26.45,
        "startTime": "2025-03-23T11:14:14",
        "records_since_previous": 51,
        "time_since_previous": "0:23:27"
    },
    {
        "crashpoint": 24.92,
        "startTime": "2025-03-23T10:50:47",
        "records_since_previous": 6,
        "time_since_previous": "0:03:54"
    },
    {
        "crashpoint": 71.13,
        "startTime": "2025-03-23T10:46:53",
        "records_since_previous": 11,
        "time_since_previous": "0:05:14"
    },
    {
        "crashpoint": 45.71,
        "startTime": "2025-03-23T10:41:39",
        "records_since_previous": 31,
        "time_since_previous": "0:13:35"
    },
    {
        "crashpoint": 21.46,
        "startTime": "2025-03-23T10:28:04",
        "records_since_previous": 29,
        "time_since_previous": "0:14:00"
    },
    {
        "crashpoint": 24.05,
        "startTime": "2025-03-23T10:14:04",
        "records_since_previous": 7,
        "time_since_previous": "0:03:24"
    },
    {
        "crashpoint": 28.95,
        "startTime": "2025-03-23T10:10:40",
        "records_since_previous": 5,
        "time_since_previous": "0:02:38"
    },
    {
        "crashpoint": 20.14,
        "startTime": "2025-03-23T10:08:02",
        "records_since_previous": 35,
        "time_since_previous": "0:15:28"
    },
    {
        "crashpoint": 25.3,
        "startTime": "2025-03-23T09:52:34",
        "records_since_previous": 9,
        "time_since_previous": "0:04:21"
    },
    {
        "crashpoint": 67.34,
        "startTime": "2025-03-23T09:48:13",
        "records_since_previous": 49,
        "time_since_previous": "0:23:05"
    },
    {
        "crashpoint": 220.51,
        "startTime": "2025-03-23T09:25:08",
        "records_since_previous": 44,
        "time_since_previous": "0:20:39"
    },
    {
        "crashpoint": 57.16,
        "startTime": "2025-03-23T09:04:29",
        "records_since_previous": 46,
        "time_since_previous": "0:20:10"
    },
    {
        "crashpoint": 108.72,
        "startTime": "2025-03-23T08:44:19",
        "records_since_previous": 22,
        "time_since_previous": "0:10:58"
    },
    {
        "crashpoint": 27.1,
        "startTime": "2025-03-23T08:33:21",
        "records_since_previous": 8,
        "time_since_previous": "0:04:33"
    },
    {
        "crashpoint": 58.38,
        "startTime": "2025-03-23T08:28:48",
        "records_since_previous": 6,
        "time_since_previous": "0:03:52"
    },
    {
        "crashpoint": 82.66,
        "startTime": "2025-03-23T08:24:56",
        "records_since_previous": 58,
        "time_since_previous": "0:24:30"
    },
    {
        "crashpoint": 27.49,
        "startTime": "2025-03-23T08:00:26",
        "records_since_previous": 33,
        "time_since_previous": "0:14:26"
    },
    {
        "crashpoint": 28.02,
        "startTime": "2025-03-23T07:46:00",
        "records_since_previous": 2,
        "time_since_previous": "0:01:27"
    },
    {
        "crashpoint": 43.51,
        "startTime": "2025-03-23T07:44:33",
        "records_since_previous": 12,
        "time_since_previous": "0:07:15"
    },
    {
        "crashpoint": 308.98,
        "startTime": "2025-03-23T07:37:18",
        "records_since_previous": 10,
        "time_since_previous": "0:05:48"
    },
    {
        "crashpoint": 1338.67,
        "startTime": "2025-03-23T07:31:30",
        "records_since_previous": 13,
        "time_since_previous": "0:06:23"
    },
    {
        "crashpoint": 27.64,
        "startTime": "2025-03-23T07:25:07",
        "records_since_previous": 6,
        "time_since_previous": "0:04:47"
    },
    {
        "crashpoint": 2107.28,
        "startTime": "2025-03-23T07:20:20",
        "records_since_previous": 7,
        "time_since_previous": "0:03:25"
    },
    {
        "crashpoint": 41.17,
        "startTime": "2025-03-23T07:16:55",
        "records_since_previous": 10,
        "time_since_previous": "0:04:42"
    },
    {
        "crashpoint": 35.53,
        "startTime": "2025-03-23T07:12:13",
        "records_since_previous": 66,
        "time_since_previous": "0:28:58"
    },
    {
        "crashpoint": 33.74,
        "startTime": "2025-03-23T06:43:15",
        "records_since_previous": 16,
        "time_since_previous": "0:07:59"
    },
    {
        "crashpoint": 113.31,
        "startTime": "2025-03-23T06:35:16",
        "records_since_previous": 5,
        "time_since_previous": "0:03:23"
    },
    {
        "crashpoint": 170.22,
        "startTime": "2025-03-23T06:31:53",
        "records_since_previous": 3,
        "time_since_previous": "0:01:45"
    },
    {
        "crashpoint": 28.66,
        "startTime": "2025-03-23T06:30:08",
        "records_since_previous": 19,
        "time_since_previous": "0:09:49"
    },
    {
        "crashpoint": 27.0,
        "startTime": "2025-03-23T06:20:19",
        "records_since_previous": 20,
        "time_since_previous": "0:08:23"
    },
    {
        "crashpoint": 19.33,
        "startTime": "2025-03-23T06:11:56",
        "records_since_previous": 39,
        "time_since_previous": "0:18:18"
    },
    {
        "crashpoint": 486.4,
        "startTime": "2025-03-23T05:53:38",
        "records_since_previous": 3,
        "time_since_previous": "0:02:27"
    },
    {
        "crashpoint": 37.28,
        "startTime": "2025-03-23T05:51:11",
        "records_since_previous": 17,
        "time_since_previous": "0:09:16"
    },
    {
        "crashpoint": 1496.63,
        "startTime": "2025-03-23T05:41:55",
        "records_since_previous": 3,
        "time_since_previous": "0:02:49"
    },
    {
        "crashpoint": 286.46,
        "startTime": "2025-03-23T05:39:06",
        "records_since_previous": 47,
        "time_since_previous": "0:22:38"
    },
    {
        "crashpoint": 56.21,
        "startTime": "2025-03-23T05:16:28",
        "records_since_previous": 4,
        "time_since_previous": "0:02:29"
    },
    {
        "crashpoint": 22.71,
        "startTime": "2025-03-23T05:13:59",
        "records_since_previous": 22,
        "time_since_previous": "0:09:56"
    },
    {
        "crashpoint": 111.06,
        "startTime": "2025-03-23T05:04:03",
        "records_since_previous": 6,
        "time_since_previous": "0:03:32"
    },
    {
        "crashpoint": 32.93,
        "startTime": "2025-03-23T05:00:31",
        "records_since_previous": 11,
        "time_since_previous": "0:04:32"
    },
    {
        "crashpoint": 20.97,
        "startTime": "2025-03-23T04:55:59",
        "records_since_previous": 48,
        "time_since_previous": "0:21:53"
    },
    {
        "crashpoint": 115.0,
        "startTime": "2025-03-23T04:34:06",
        "records_since_previous": 77,
        "time_since_previous": "0:33:10"
    },
    {
        "crashpoint": 24.18,
        "startTime": "2025-03-23T04:00:56",
        "records_since_previous": 1,
        "time_since_previous": "0:01:53"
    },
    {
        "crashpoint": 445.22,
        "startTime": "2025-03-23T03:59:03",
        "records_since_previous": 79,
        "time_since_previous": "0:39:18"
    },
    {
        "crashpoint": 41.98,
        "startTime": "2025-03-23T03:19:45",
        "records_since_previous": 9,
        "time_since_previous": "0:04:09"
    },
    {
        "crashpoint": 246.11,
        "startTime": "2025-03-23T03:15:36",
        "records_since_previous": 27,
        "time_since_previous": "0:11:18"
    },
    {
        "crashpoint": 19.44,
        "startTime": "2025-03-23T03:04:18",
        "records_since_previous": 5,
        "time_since_previous": "0:03:19"
    },
    {
        "crashpoint": 36.63,
        "startTime": "2025-03-23T03:00:59",
        "records_since_previous": 87,
        "time_since_previous": "0:36:37"
    },
    {
        "crashpoint": 102.12,
        "startTime": "2025-03-23T02:24:22",
        "records_since_previous": 5,
        "time_since_previous": "0:02:15"
    },
    {
        "crashpoint": 23.07,
        "startTime": "2025-03-23T02:22:07",
        "records_since_previous": 13,
        "time_since_previous": "0:05:40"
    },
    {
        "crashpoint": 46.85,
        "startTime": "2025-03-23T02:16:27",
        "records_since_previous": 1,
        "time_since_previous": "0:01:43"
    },
    {
        "crashpoint": 239.45,
        "startTime": "2025-03-23T02:14:44",
        "records_since_previous": 4,
        "time_since_previous": "0:02:10"
    },
    {
        "crashpoint": 21.06,
        "startTime": "2025-03-23T02:12:34",
        "records_since_previous": 20,
        "time_since_previous": "0:09:13"
    },
    {
        "crashpoint": 31.43,
        "startTime": "2025-03-23T02:03:21",
        "records_since_previous": 22,
        "time_since_previous": "0:08:53"
    },
    {
        "crashpoint": 33.09,
        "startTime": "2025-03-23T01:54:28",
        "records_since_previous": 1,
        "time_since_previous": "0:01:06"
    },
    {
        "crashpoint": 27.32,
        "startTime": "2025-03-23T01:53:22",
        "records_since_previous": 55,
        "time_since_previous": "0:25:15"
    },
    {
        "crashpoint": 19.65,
        "startTime": "2025-03-23T01:28:07",
        "records_since_previous": 72,
        "time_since_previous": "0:33:10"
    },
    {
        "crashpoint": 49.6,
        "startTime": "2025-03-23T00:54:57",
        "records_since_previous": 6,
        "time_since_previous": "0:03:16"
    },
    {
        "crashpoint": 316.05,
        "startTime": "2025-03-23T00:51:41",
        "records_since_previous": 6,
        "time_since_previous": "0:03:30"
    },
    {
        "crashpoint": 22.39,
        "startTime": "2025-03-23T00:48:11",
        "records_since_previous": 2,
        "time_since_previous": "0:02:42"
    },
    {
        "crashpoint": 3411.47,
        "startTime": "2025-03-23T00:45:29",
        "records_since_previous": 11,
        "time_since_previous": "0:06:35"
    },
    {
        "crashpoint": 167.24,
        "startTime": "2025-03-23T00:38:54",
        "records_since_previous": 4,
        "time_since_previous": "0:02:46"
    },
    {
        "crashpoint": 64.65,
        "startTime": "2025-03-23T00:36:08",
        "records_since_previous": 26,
        "time_since_previous": "0:12:04"
    },
    {
        "crashpoint": 20.47,
        "startTime": "2025-03-23T00:24:04",
        "records_since_previous": 30,
        "time_since_previous": "0:15:28"
    },
    {
        "crashpoint": 362.32,
        "startTime": "2025-03-23T00:08:36",
        "records_since_previous": 12,
        "time_since_previous": "0:05:55"
    },
    {
        "crashpoint": 25.48,
        "startTime": "2025-03-23T00:02:41",
        "records_since_previous": 10,
        "time_since_previous": "0:04:25"
    },
    {
        "crashpoint": 23.89,
        "startTime": "2025-03-22T23:58:16",
        "records_since_previous": 9,
        "time_since_previous": "0:05:37"
    },
    {
        "crashpoint": 167.43,
        "startTime": "2025-03-22T23:52:39",
        "records_since_previous": 40,
        "time_since_previous": "0:16:51"
    },
    {
        "crashpoint": 31.5,
        "startTime": "2025-03-22T23:35:48",
        "records_since_previous": 10,
        "time_since_previous": "0:04:32"
    },
    {
        "crashpoint": 27.43,
        "startTime": "2025-03-22T23:31:16",
        "records_since_previous": 18,
        "time_since_previous": "0:07:09"
    },
    {
        "crashpoint": 20.23,
        "startTime": "2025-03-22T23:24:07",
        "records_since_previous": 4,
        "time_since_previous": "0:02:15"
    },
    {
        "crashpoint": 21.98,
        "startTime": "2025-03-22T23:21:52",
        "records_since_previous": 62,
        "time_since_previous": "0:25:47"
    },
    {
        "crashpoint": 60.56,
        "startTime": "2025-03-22T22:56:05",
        "records_since_previous": 66,
        "time_since_previous": "0:29:25"
    },
    {
        "crashpoint": 24.58,
        "startTime": "2025-03-22T22:26:40",
        "records_since_previous": 1,
        "time_since_previous": "0:01:29"
    },
    {
        "crashpoint": 100.01,
        "startTime": "2025-03-22T22:25:11",
        "records_since_previous": 23,
        "time_since_previous": "0:10:35"
    },
    {
        "crashpoint": 97.67,
        "startTime": "2025-03-22T22:14:36",
        "records_since_previous": 8,
        "time_since_previous": "0:04:03"
    },
    {
        "crashpoint": 25.66,
        "startTime": "2025-03-22T22:10:33",
        "records_since_previous": 95,
        "time_since_previous": "0:39:45"
    },
    {
        "crashpoint": 37.6,
        "startTime": "2025-03-22T21:30:48",
        "records_since_previous": 3,
        "time_since_previous": "0:01:59"
    },
    {
        "crashpoint": 49.03,
        "startTime": "2025-03-22T21:28:49",
        "records_since_previous": 25,
        "time_since_previous": "0:11:49"
    },
    {
        "crashpoint": 65.39,
        "startTime": "2025-03-22T21:17:00",
        "records_since_previous": 40,
        "time_since_previous": "0:18:43"
    },
    {
        "crashpoint": 96.03,
        "startTime": "2025-03-22T20:58:17",
        "records_since_previous": 23,
        "time_since_previous": "0:11:44"
    },
    {
        "crashpoint": 22.14,
        "startTime": "2025-03-22T20:46:33",
        "records_since_previous": 5,
        "time_since_previous": "0:03:37"
    },
    {
        "crashpoint": 69.06,
        "startTime": "2025-03-22T20:42:56",
        "records_since_previous": 3,
        "time_since_previous": "0:02:11"
    },
    {
        "crashpoint": 23.68,
        "startTime": "2025-03-22T20:40:45",
        "records_since_previous": 20,
        "time_since_previous": "0:09:08"
    },
    {
        "crashpoint": 116.34,
        "startTime": "2025-03-22T20:31:37",
        "records_since_previous": 17,
        "time_since_previous": "0:07:42"
    },
    {
        "crashpoint": 39.8,
        "startTime": "2025-03-22T20:23:55",
        "records_since_previous": 11,
        "time_since_previous": "0:05:30"
    },
    {
        "crashpoint": 25.21,
        "startTime": "2025-03-22T20:18:25",
        "records_since_previous": 13,
        "time_since_previous": "0:06:03"
    },
    {
        "crashpoint": 110.22,
        "startTime": "2025-03-22T20:12:22",
        "records_since_previous": 11,
        "time_since_previous": "0:05:40"
    },
    {
        "crashpoint": 181.16,
        "startTime": "2025-03-22T20:06:42",
        "records_since_previous": 11,
        "time_since_previous": "0:04:44"
    },
    {
        "crashpoint": 27.09,
        "startTime": "2025-03-22T20:01:58",
        "records_since_previous": 18,
        "time_since_previous": "0:08:31"
    },
    {
        "crashpoint": 36.32,
        "startTime": "2025-03-22T19:53:27",
        "records_since_previous": 8,
        "time_since_previous": "0:03:32"
    },
    {
        "crashpoint": 26.66,
        "startTime": "2025-03-22T19:49:55",
        "records_since_previous": 86,
        "time_since_previous": "0:36:51"
    },
    {
        "crashpoint": 38.36,
        "startTime": "2025-03-22T19:13:04",
        "records_since_previous": 45,
        "time_since_previous": "0:18:20"
    },
    {
        "crashpoint": 35.16,
        "startTime": "2025-03-22T18:54:44",
        "records_since_previous": 6,
        "time_since_previous": "0:04:14"
    },
    {
        "crashpoint": 60.23,
        "startTime": "2025-03-22T18:50:30",
        "records_since_previous": 21,
        "time_since_previous": "0:10:30"
    },
    {
        "crashpoint": 59.81,
        "startTime": "2025-03-22T18:40:00",
        "records_since_previous": 6,
        "time_since_previous": "0:04:55"
    },
    {
        "crashpoint": 884.41,
        "startTime": "2025-03-22T18:35:05",
        "records_since_previous": 5,
        "time_since_previous": "0:03:11"
    },
    {
        "crashpoint": 19.29,
        "startTime": "2025-03-22T18:31:54",
        "records_since_previous": 6,
        "time_since_previous": "0:03:18"
    },
    {
        "crashpoint": 22.05,
        "startTime": "2025-03-22T18:28:36",
        "records_since_previous": 15,
        "time_since_previous": "0:07:37"
    },
    {
        "crashpoint": 61.0,
        "startTime": "2025-03-22T18:20:59",
        "records_since_previous": 13,
        "time_since_previous": "0:05:46"
    },
    {
        "crashpoint": 24.3,
        "startTime": "2025-03-22T18:15:13",
        "records_since_previous": 3,
        "time_since_previous": "0:01:29"
    },
    {
        "crashpoint": 21.18,
        "startTime": "2025-03-22T18:13:44",
        "records_since_previous": 18,
        "time_since_previous": "0:07:46"
    },
    {
        "crashpoint": 29.77,
        "startTime": "2025-03-22T18:05:58",
        "records_since_previous": 12,
        "time_since_previous": "0:06:31"
    },
    {
        "crashpoint": 180.99,
        "startTime": "2025-03-22T17:59:27",
        "records_since_previous": 5,
        "time_since_previous": "0:02:51"
    },
    {
        "crashpoint": 19.98,
        "startTime": "2025-03-22T17:56:36",
        "records_since_previous": 6,
        "time_since_previous": "0:02:51"
    },
    {
        "crashpoint": 31.72,
        "startTime": "2025-03-22T17:53:45",
        "records_since_previous": 22,
        "time_since_previous": "0:11:17"
    },
    {
        "crashpoint": 171.77,
        "startTime": "2025-03-22T17:42:28",
        "records_since_previous": 39,
        "time_since_previous": "0:17:24"
    },
    {
        "crashpoint": 66.12,
        "startTime": "2025-03-22T17:25:04",
        "records_since_previous": 26,
        "time_since_previous": "0:13:39"
    },
    {
        "crashpoint": 59.91,
        "startTime": "2025-03-22T17:11:25",
        "records_since_previous": 9,
        "time_since_previous": "0:05:21"
    },
    {
        "crashpoint": 30.24,
        "startTime": "2025-03-22T17:06:04",
        "records_since_previous": 12,
        "time_since_previous": "0:05:22"
    },
    {
        "crashpoint": 24.26,
        "startTime": "2025-03-22T17:00:42",
        "records_since_previous": 56,
        "time_since_previous": "0:24:57"
    },
    {
        "crashpoint": 97.35,
        "startTime": "2025-03-22T16:35:45",
        "records_since_previous": 43,
        "time_since_previous": "0:19:43"
    },
    {
        "crashpoint": 19.79,
        "startTime": "2025-03-22T16:16:02",
        "records_since_previous": 15,
        "time_since_previous": "0:07:50"
    },
    {
        "crashpoint": 71.1,
        "startTime": "2025-03-22T16:08:12",
        "records_since_previous": 1,
        "time_since_previous": "0:01:04"
    },
    {
        "crashpoint": 23.43,
        "startTime": "2025-03-22T16:07:08",
        "records_since_previous": 9,
        "time_since_previous": "0:04:20"
    },
    {
        "crashpoint": 19.68,
        "startTime": "2025-03-22T16:02:48",
        "records_since_previous": 2,
        "time_since_previous": "0:01:22"
    },
    {
        "crashpoint": 32.17,
        "startTime": "2025-03-22T16:01:26",
        "records_since_previous": 5,
        "time_since_previous": "0:02:38"
    },
    {
        "crashpoint": 29.68,
        "startTime": "2025-03-22T15:58:48",
        "records_since_previous": 1,
        "time_since_previous": "0:01:13"
    },
    {
        "crashpoint": 39.81,
        "startTime": "2025-03-22T15:57:35",
        "records_since_previous": 3,
        "time_since_previous": "0:02:09"
    },
    {
        "crashpoint": 50.19,
        "startTime": "2025-03-22T15:55:26",
        "records_since_previous": 22,
        "time_since_previous": "0:09:10"
    },
    {
        "crashpoint": 23.27,
        "startTime": "2025-03-22T15:46:16",
        "records_since_previous": 9,
        "time_since_previous": "0:04:57"
    },
    {
        "crashpoint": 55.64,
        "startTime": "2025-03-22T15:41:19",
        "records_since_previous": 20,
        "time_since_previous": "0:10:37"
    },
    {
        "crashpoint": 5534.93,
        "startTime": "2025-03-22T15:30:42",
        "records_since_previous": 2,
        "time_since_previous": "0:01:28"
    },
    {
        "crashpoint": 45.84,
        "startTime": "2025-03-22T15:29:14",
        "records_since_previous": 18,
        "time_since_previous": "0:08:46"
    },
    {
        "crashpoint": 152.32,
        "startTime": "2025-03-22T15:20:28",
        "records_since_previous": 20,
        "time_since_previous": "0:08:32"
    },
    {
        "crashpoint": 31.1,
        "startTime": "2025-03-22T15:11:56",
        "records_since_previous": 43,
        "time_since_previous": "0:19:11"
    },
    {
        "crashpoint": 205.7,
        "startTime": "2025-03-22T14:52:45",
        "records_since_previous": 33,
        "time_since_previous": "0:15:34"
    },
    {
        "crashpoint": 31.21,
        "startTime": "2025-03-22T14:37:11",
        "records_since_previous": 36,
        "time_since_previous": "0:17:09"
    },
    {
        "crashpoint": 27.04,
        "startTime": "2025-03-22T14:20:02",
        "records_since_previous": 14,
        "time_since_previous": "0:06:30"
    },
    {
        "crashpoint": 40.62,
        "startTime": "2025-03-22T14:13:32",
        "records_since_previous": 56,
        "time_since_previous": "0:21:34"
    },
    {
        "crashpoint": 23.64,
        "startTime": "2025-03-22T13:51:58",
        "records_since_previous": 4,
        "time_since_previous": "0:02:30"
    },
    {
        "crashpoint": 34.42,
        "startTime": "2025-03-22T13:49:28",
        "records_since_previous": 7,
        "time_since_previous": "0:04:06"
    },
    {
        "crashpoint": 72.14,
        "startTime": "2025-03-22T13:45:22",
        "records_since_previous": 9,
        "time_since_previous": "0:05:41"
    },
    {
        "crashpoint": 61.94,
        "startTime": "2025-03-22T13:39:41",
        "records_since_previous": 13,
        "time_since_previous": "0:06:04"
    },
    {
        "crashpoint": 26.21,
        "startTime": "2025-03-22T13:33:37",
        "records_since_previous": 15,
        "time_since_previous": "0:08:08"
    },
    {
        "crashpoint": 36.84,
        "startTime": "2025-03-22T13:25:29",
        "records_since_previous": 38,
        "time_since_previous": "0:15:11"
    },
    {
        "crashpoint": 23.8,
        "startTime": "2025-03-22T13:10:18",
        "records_since_previous": 28,
        "time_since_previous": "0:14:12"
    },
    {
        "crashpoint": 31.52,
        "startTime": "2025-03-22T12:56:06",
        "records_since_previous": 18,
        "time_since_previous": "0:09:13"
    },
    {
        "crashpoint": 1330.76,
        "startTime": "2025-03-22T12:46:53",
        "records_since_previous": 16,
        "time_since_previous": "0:08:08"
    },
    {
        "crashpoint": 125.96,
        "startTime": "2025-03-22T12:38:45",
        "records_since_previous": 5,
        "time_since_previous": "0:02:52"
    },
    {
        "crashpoint": 20.71,
        "startTime": "2025-03-22T12:35:53",
        "records_since_previous": 9,
        "time_since_previous": "0:04:24"
    },
    {
        "crashpoint": 20.42,
        "startTime": "2025-03-22T12:31:29",
        "records_since_previous": 6,
        "time_since_previous": "0:03:18"
    },
    {
        "crashpoint": 70.14,
        "startTime": "2025-03-22T12:28:11",
        "records_since_previous": 1,
        "time_since_previous": "0:01:52"
    },
    {
        "crashpoint": 411.69,
        "startTime": "2025-03-22T12:26:19",
        "records_since_previous": 13,
        "time_since_previous": "0:05:49"
    },
    {
        "crashpoint": 19.18,
        "startTime": "2025-03-22T12:20:30",
        "records_since_previous": 15,
        "time_since_previous": "0:06:37"
    },
    {
        "crashpoint": 25.66,
        "startTime": "2025-03-22T12:13:53",
        "records_since_previous": 19,
        "time_since_previous": "0:10:09"
    },
    {
        "crashpoint": 30.54,
        "startTime": "2025-03-22T12:03:44",
        "records_since_previous": 14,
        "time_since_previous": "0:08:03"
    },
    {
        "crashpoint": 49.88,
        "startTime": "2025-03-22T11:55:41",
        "records_since_previous": 3,
        "time_since_previous": "0:02:04"
    },
    {
        "crashpoint": 25.01,
        "startTime": "2025-03-22T11:53:37",
        "records_since_previous": 8,
        "time_since_previous": "0:03:53"
    },
    {
        "crashpoint": 32.95,
        "startTime": "2025-03-22T11:49:44",
        "records_since_previous": 25,
        "time_since_previous": "0:12:30"
    },
    {
        "crashpoint": 489.17,
        "startTime": "2025-03-22T11:37:14",
        "records_since_previous": 6,
        "time_since_previous": "0:03:44"
    },
    {
        "crashpoint": 19.58,
        "startTime": "2025-03-22T11:33:30",
        "records_since_previous": 2,
        "time_since_previous": "0:01:42"
    },
    {
        "crashpoint": 113.54,
        "startTime": "2025-03-22T11:31:48",
        "records_since_previous": 3,
        "time_since_previous": "0:01:52"
    },
    {
        "crashpoint": 20.0,
        "startTime": "2025-03-22T11:29:56",
        "records_since_previous": 9,
        "time_since_previous": "0:03:42"
    },
    {
        "crashpoint": 20.73,
        "startTime": "2025-03-22T11:26:14",
        "records_since_previous": 11,
        "time_since_previous": "0:05:49"
    },
    {
        "crashpoint": 133.87,
        "startTime": "2025-03-22T11:20:25",
        "records_since_previous": 22,
        "time_since_previous": "0:11:33"
    },
    {
        "crashpoint": 142.0,
        "startTime": "2025-03-22T11:08:52",
        "records_since_previous": 23,
        "time_since_previous": "0:11:14"
    },
    {
        "crashpoint": 23.6,
        "startTime": "2025-03-22T10:57:38",
        "records_since_previous": 15,
        "time_since_previous": "0:06:39"
    },
    {
        "crashpoint": 66.69,
        "startTime": "2025-03-22T10:50:59",
        "records_since_previous": 5,
        "time_since_previous": "0:02:38"
    },
    {
        "crashpoint": 20.14,
        "startTime": "2025-03-22T10:48:21",
        "records_since_previous": 5,
        "time_since_previous": "0:02:43"
    },
    {
        "crashpoint": 25.74,
        "startTime": "2025-03-22T10:45:38",
        "records_since_previous": 27,
        "time_since_previous": "0:11:22"
    },
    {
        "crashpoint": 30.56,
        "startTime": "2025-03-22T10:34:16",
        "records_since_previous": 48,
        "time_since_previous": "0:20:38"
    },
    {
        "crashpoint": 22.2,
        "startTime": "2025-03-22T10:13:38",
        "records_since_previous": 10,
        "time_since_previous": "0:05:04"
    },
    {
        "crashpoint": 28.23,
        "startTime": "2025-03-22T10:08:34",
        "records_since_previous": 6,
        "time_since_previous": "0:02:30"
    },
    {
        "crashpoint": 21.12,
        "startTime": "2025-03-22T10:06:04",
        "records_since_previous": 3,
        "time_since_previous": "0:02:01"
    },
    {
        "crashpoint": 26.04,
        "startTime": "2025-03-22T10:04:03",
        "records_since_previous": 33,
        "time_since_previous": "0:15:02"
    },
    {
        "crashpoint": 424.25,
        "startTime": "2025-03-22T09:49:01",
        "records_since_previous": 34,
        "time_since_previous": "0:17:08"
    },
    {
        "crashpoint": 30.9,
        "startTime": "2025-03-22T09:31:53",
        "records_since_previous": 38,
        "time_since_previous": "0:15:09"
    },
    {
        "crashpoint": 19.21,
        "startTime": "2025-03-22T09:16:44",
        "records_since_previous": 19,
        "time_since_previous": "0:09:09"
    },
    {
        "crashpoint": 103.35,
        "startTime": "2025-03-22T09:07:35",
        "records_since_previous": 12,
        "time_since_previous": "0:06:21"
    },
    {
        "crashpoint": 74.71,
        "startTime": "2025-03-22T09:01:14",
        "records_since_previous": 6,
        "time_since_previous": "0:03:57"
    },
    {
        "crashpoint": 40.65,
        "startTime": "2025-03-22T08:57:17",
        "records_since_previous": 9,
        "time_since_previous": "0:05:16"
    },
    {
        "crashpoint": 19.98,
        "startTime": "2025-03-22T08:52:01",
        "records_since_previous": 62,
        "time_since_previous": "0:26:28"
    },
    {
        "crashpoint": 58.82,
        "startTime": "2025-03-22T08:25:33",
        "records_since_previous": 7,
        "time_since_previous": "0:03:51"
    },
    {
        "crashpoint": 31.2,
        "startTime": "2025-03-22T08:21:42",
        "records_since_previous": 15,
        "time_since_previous": "0:07:40"
    },
    {
        "crashpoint": 21.73,
        "startTime": "2025-03-22T08:14:02",
        "records_since_previous": 43,
        "time_since_previous": "0:16:08"
    },
    {
        "crashpoint": 21.71,
        "startTime": "2025-03-22T07:57:54",
        "records_since_previous": 12,
        "time_since_previous": "0:06:54"
    },
    {
        "crashpoint": 2101.29,
        "startTime": "2025-03-22T07:51:00",
        "records_since_previous": 2,
        "time_since_previous": "0:01:28"
    },
    {
        "crashpoint": 27.15,
        "startTime": "2025-03-22T07:49:32",
        "records_since_previous": 7,
        "time_since_previous": "0:03:09"
    },
    {
        "crashpoint": 48.93,
        "startTime": "2025-03-22T07:46:23",
        "records_since_previous": 3,
        "time_since_previous": "0:01:54"
    },
    {
        "crashpoint": 38.73,
        "startTime": "2025-03-22T07:44:29",
        "records_since_previous": 4,
        "time_since_previous": "0:02:38"
    },
    {
        "crashpoint": 30.52,
        "startTime": "2025-03-22T07:41:51",
        "records_since_previous": 38,
        "time_since_previous": "0:17:36"
    },
    {
        "crashpoint": 83.77,
        "startTime": "2025-03-22T07:24:15",
        "records_since_previous": 13,
        "time_since_previous": "0:07:35"
    },
    {
        "crashpoint": 27.6,
        "startTime": "2025-03-22T07:16:40",
        "records_since_previous": 54,
        "time_since_previous": "0:24:31"
    },
    {
        "crashpoint": 34.29,
        "startTime": "2025-03-22T06:52:09",
        "records_since_previous": 23,
        "time_since_previous": "0:10:20"
    },
    {
        "crashpoint": 23.28,
        "startTime": "2025-03-22T06:41:49",
        "records_since_previous": 4,
        "time_since_previous": "0:03:43"
    },
    {
        "crashpoint": 176.26,
        "startTime": "2025-03-22T06:38:06",
        "records_since_previous": 1,
        "time_since_previous": "0:01:28"
    },
    {
        "crashpoint": 97.92,
        "startTime": "2025-03-22T06:36:38",
        "records_since_previous": 24,
        "time_since_previous": "0:10:05"
    },
    {
        "crashpoint": 221.97,
        "startTime": "2025-03-22T06:26:33",
        "records_since_previous": 39,
        "time_since_previous": "0:15:46"
    },
    {
        "crashpoint": 55.34,
        "startTime": "2025-03-22T06:10:47",
        "records_since_previous": 40,
        "time_since_previous": "0:18:51"
    },
    {
        "crashpoint": 57.1,
        "startTime": "2025-03-22T05:51:56",
        "records_since_previous": 9,
        "time_since_previous": "0:05:18"
    },
    {
        "crashpoint": 68.54,
        "startTime": "2025-03-22T05:46:38",
        "records_since_previous": 1,
        "time_since_previous": "0:01:06"
    },
    {
        "crashpoint": 25.64,
        "startTime": "2025-03-22T05:45:32",
        "records_since_previous": 7,
        "time_since_previous": "0:03:47"
    },
    {
        "crashpoint": 70.38,
        "startTime": "2025-03-22T05:41:45",
        "records_since_previous": 11,
        "time_since_previous": "0:06:03"
    },
    {
        "crashpoint": 49.16,
        "startTime": "2025-03-22T05:35:42",
        "records_since_previous": 55,
        "time_since_previous": "0:25:23"
    },
    {
        "crashpoint": 272.33,
        "startTime": "2025-03-22T05:10:19",
        "records_since_previous": 21,
        "time_since_previous": "0:10:19"
    },
    {
        "crashpoint": 29.58,
        "startTime": "2025-03-22T05:00:00",
        "records_since_previous": 34,
        "time_since_previous": "0:14:07"
    },
    {
        "crashpoint": 53.2,
        "startTime": "2025-03-22T04:45:53",
        "records_since_previous": 10,
        "time_since_previous": "0:04:38"
    },
    {
        "crashpoint": 29.49,
        "startTime": "2025-03-22T04:41:15",
        "records_since_previous": 3,
        "time_since_previous": "0:02:42"
    },
    {
        "crashpoint": 365.44,
        "startTime": "2025-03-22T04:38:33",
        "records_since_previous": 50,
        "time_since_previous": "0:22:37"
    },
    {
        "crashpoint": 20.7,
        "startTime": "2025-03-22T04:15:56",
        "records_since_previous": 19,
        "time_since_previous": "0:07:17"
    },
    {
        "crashpoint": 31.17,
        "startTime": "2025-03-22T04:08:39",
        "records_since_previous": 5,
        "time_since_previous": "0:02:49"
    },
    {
        "crashpoint": 42.85,
        "startTime": "2025-03-22T04:05:50",
        "records_since_previous": 3,
        "time_since_previous": "0:01:52"
    },
    {
        "crashpoint": 20.37,
        "startTime": "2025-03-22T04:03:58",
        "records_since_previous": 1,
        "time_since_previous": "0:01:15"
    },
    {
        "crashpoint": 43.99,
        "startTime": "2025-03-22T04:02:43",
        "records_since_previous": 7,
        "time_since_previous": "0:03:20"
    },
    {
        "crashpoint": 26.08,
        "startTime": "2025-03-22T03:59:23",
        "records_since_previous": 5,
        "time_since_previous": "0:02:52"
    },
    {
        "crashpoint": 106.59,
        "startTime": "2025-03-22T03:56:31",
        "records_since_previous": 1,
        "time_since_previous": "0:01:09"
    },
    {
        "crashpoint": 31.72,
        "startTime": "2025-03-22T03:55:22",
        "records_since_previous": 26,
        "time_since_previous": "0:12:11"
    },
    {
        "crashpoint": 111.56,
        "startTime": "2025-03-22T03:43:11",
        "records_since_previous": 13,
        "time_since_previous": "0:07:29"
    },
    {
        "crashpoint": 139.25,
        "startTime": "2025-03-22T03:35:42",
        "records_since_previous": 42,
        "time_since_previous": "0:17:46"
    },
    {
        "crashpoint": 37.65,
        "startTime": "2025-03-22T03:17:56",
        "records_since_previous": 9,
        "time_since_previous": "0:04:05"
    },
    {
        "crashpoint": 23.07,
        "startTime": "2025-03-22T03:13:51",
        "records_since_previous": 1,
        "time_since_previous": "0:01:38"
    },
    {
        "crashpoint": 174.15,
        "startTime": "2025-03-22T03:12:13",
        "records_since_previous": 58,
        "time_since_previous": "0:24:59"
    },
    {
        "crashpoint": 68.61,
        "startTime": "2025-03-22T02:47:14",
        "records_since_previous": 2,
        "time_since_previous": "0:01:42"
    },
    {
        "crashpoint": 81.18,
        "startTime": "2025-03-22T02:45:32",
        "records_since_previous": 1,
        "time_since_previous": "0:01:01"
    },
    {
        "crashpoint": 19.46,
        "startTime": "2025-03-22T02:44:31",
        "records_since_previous": 17,
        "time_since_previous": "0:07:22"
    },
    {
        "crashpoint": 42.15,
        "startTime": "2025-03-22T02:37:09",
        "records_since_previous": 2,
        "time_since_previous": "0:01:24"
    },
    {
        "crashpoint": 22.85,
        "startTime": "2025-03-22T02:35:45",
        "records_since_previous": 17,
        "time_since_previous": "0:06:50"
    },
    {
        "crashpoint": 32.42,
        "startTime": "2025-03-22T02:28:55",
        "records_since_previous": 25,
        "time_since_previous": "0:12:19"
    },
    {
        "crashpoint": 65.16,
        "startTime": "2025-03-22T02:16:36",
        "records_since_previous": 15,
        "time_since_previous": "0:07:30"
    },
    {
        "crashpoint": 24.01,
        "startTime": "2025-03-22T02:09:06",
        "records_since_previous": 14,
        "time_since_previous": "0:06:40"
    },
    {
        "crashpoint": 33.87,
        "startTime": "2025-03-22T02:02:26",
        "records_since_previous": 5,
        "time_since_previous": "0:02:46"
    },
    {
        "crashpoint": 30.26,
        "startTime": "2025-03-22T01:59:40",
        "records_since_previous": 4,
        "time_since_previous": "0:02:19"
    },
    {
        "crashpoint": 23.24,
        "startTime": "2025-03-22T01:57:21",
        "records_since_previous": 3,
        "time_since_previous": "0:01:59"
    },
    {
        "crashpoint": 36.48,
        "startTime": "2025-03-22T01:55:22",
        "records_since_previous": 27,
        "time_since_previous": "0:12:35"
    },
    {
        "crashpoint": 61.58,
        "startTime": "2025-03-22T01:42:47",
        "records_since_previous": 13,
        "time_since_previous": "0:06:15"
    },
    {
        "crashpoint": 73.98,
        "startTime": "2025-03-22T01:36:32",
        "records_since_previous": 16,
        "time_since_previous": "0:07:54"
    },
    {
        "crashpoint": 33.07,
        "startTime": "2025-03-22T01:28:38",
        "records_since_previous": 10,
        "time_since_previous": "0:04:51"
    },
    {
        "crashpoint": 108.71,
        "startTime": "2025-03-22T01:23:47",
        "records_since_previous": 83,
        "time_since_previous": "0:36:22"
    },
    {
        "crashpoint": 31.08,
        "startTime": "2025-03-22T00:47:25",
        "records_since_previous": 16,
        "time_since_previous": "0:08:00"
    },
    {
        "crashpoint": 27.56,
        "startTime": "2025-03-22T00:39:25",
        "records_since_previous": 16,
        "time_since_previous": "0:07:32"
    },
    {
        "crashpoint": 84.93,
        "startTime": "2025-03-22T00:31:53",
        "records_since_previous": 14,
        "time_since_previous": "0:06:43"
    },
    {
        "crashpoint": 36.87,
        "startTime": "2025-03-22T00:25:10",
        "records_since_previous": 6,
        "time_since_previous": "0:03:13"
    },
    {
        "crashpoint": 109.33,
        "startTime": "2025-03-22T00:21:57",
        "records_since_previous": 66,
        "time_since_previous": "0:29:50"
    },
    {
        "crashpoint": 71.02,
        "startTime": "2025-03-21T23:52:07",
        "records_since_previous": 3,
        "time_since_previous": "0:01:36"
    },
    {
        "crashpoint": 26.59,
        "startTime": "2025-03-21T23:50:31",
        "records_since_previous": 21,
        "time_since_previous": "0:08:55"
    },
    {
        "crashpoint": 20.84,
        "startTime": "2025-03-21T23:41:36",
        "records_since_previous": 14,
        "time_since_previous": "0:05:44"
    },
    {
        "crashpoint": 33.97,
        "startTime": "2025-03-21T23:35:52",
        "records_since_previous": 20,
        "time_since_previous": "0:09:27"
    },
    {
        "crashpoint": 51.76,
        "startTime": "2025-03-21T23:26:25",
        "records_since_previous": 40,
        "time_since_previous": "0:16:10"
    },
    {
        "crashpoint": 38.83,
        "startTime": "2025-03-21T23:10:15",
        "records_since_previous": 12,
        "time_since_previous": "0:06:13"
    },
    {
        "crashpoint": 635.35,
        "startTime": "2025-03-21T23:04:02",
        "records_since_previous": 18,
        "time_since_previous": "0:08:56"
    },
    {
        "crashpoint": 33.36,
        "startTime": "2025-03-21T22:55:06",
        "records_since_previous": 33,
        "time_since_previous": "0:13:57"
    },
    {
        "crashpoint": 94.88,
        "startTime": "2025-03-21T22:41:09",
        "records_since_previous": 4,
        "time_since_previous": "0:01:57"
    },
    {
        "crashpoint": 22.13,
        "startTime": "2025-03-21T22:39:12",
        "records_since_previous": 2,
        "time_since_previous": "0:01:54"
    },
    {
        "crashpoint": 216.57,
        "startTime": "2025-03-21T22:37:18",
        "records_since_previous": 5,
        "time_since_previous": "0:02:49"
    },
    {
        "crashpoint": 41.53,
        "startTime": "2025-03-21T22:34:29",
        "records_since_previous": 47,
        "time_since_previous": "0:21:44"
    },
    {
        "crashpoint": 26.5,
        "startTime": "2025-03-21T22:12:45",
        "records_since_previous": 86,
        "time_since_previous": "0:38:06"
    },
    {
        "crashpoint": 28.68,
        "startTime": "2025-03-21T21:34:39",
        "records_since_previous": 1,
        "time_since_previous": "0:01:02"
    },
    {
        "crashpoint": 20.49,
        "startTime": "2025-03-21T21:33:37",
        "records_since_previous": 6,
        "time_since_previous": "0:03:13"
    },
    {
        "crashpoint": 31.51,
        "startTime": "2025-03-21T21:30:24",
        "records_since_previous": 2,
        "time_since_previous": "0:01:21"
    },
    {
        "crashpoint": 21.14,
        "startTime": "2025-03-21T21:29:03",
        "records_since_previous": 10,
        "time_since_previous": "0:05:58"
    },
    {
        "crashpoint": 137.51,
        "startTime": "2025-03-21T21:23:05",
        "records_since_previous": 10,
        "time_since_previous": "0:04:58"
    },
    {
        "crashpoint": 96.49,
        "startTime": "2025-03-21T21:18:07",
        "records_since_previous": 68,
        "time_since_previous": "0:28:59"
    },
    {
        "crashpoint": 134.57,
        "startTime": "2025-03-21T20:49:08",
        "records_since_previous": 10,
        "time_since_previous": "0:05:26"
    },
    {
        "crashpoint": 364.33,
        "startTime": "2025-03-21T20:43:42",
        "records_since_previous": 38,
        "time_since_previous": "0:16:09"
    },
    {
        "crashpoint": 21.89,
        "startTime": "2025-03-21T20:27:33",
        "records_since_previous": 52,
        "time_since_previous": "0:25:13"
    },
    {
        "crashpoint": 86.77,
        "startTime": "2025-03-21T20:02:20",
        "records_since_previous": 3,
        "time_since_previous": "0:02:22"
    },
    {
        "crashpoint": 58.5,
        "startTime": "2025-03-21T19:59:58",
        "records_since_previous": 36,
        "time_since_previous": "0:18:33"
    },
    {
        "crashpoint": 55.74,
        "startTime": "2025-03-21T19:41:25",
        "records_since_previous": 5,
        "time_since_previous": "0:02:23"
    },
    {
        "crashpoint": 51.36,
        "startTime": "2025-03-21T19:39:02",
        "records_since_previous": 5,
        "time_since_previous": "0:02:44"
    },
    {
        "crashpoint": 31.2,
        "startTime": "2025-03-21T19:36:18",
        "records_since_previous": 24,
        "time_since_previous": "0:10:59"
    },
    {
        "crashpoint": 35.31,
        "startTime": "2025-03-21T19:25:19",
        "records_since_previous": 4,
        "time_since_previous": "0:03:30"
    },
    {
        "crashpoint": 120.44,
        "startTime": "2025-03-21T19:21:49",
        "records_since_previous": 2,
        "time_since_previous": "0:01:37"
    },
    {
        "crashpoint": 64.49,
        "startTime": "2025-03-21T19:20:12",
        "records_since_previous": 8,
        "time_since_previous": "0:04:09"
    },
    {
        "crashpoint": 87.56,
        "startTime": "2025-03-21T19:16:03",
        "records_since_previous": 24,
        "time_since_previous": "0:11:48"
    },
    {
        "crashpoint": 220.03,
        "startTime": "2025-03-21T19:04:15",
        "records_since_previous": 7,
        "time_since_previous": "0:03:11"
    },
    {
        "crashpoint": 23.18,
        "startTime": "2025-03-21T19:01:04",
        "records_since_previous": 29,
        "time_since_previous": "0:12:12"
    },
    {
        "crashpoint": 63.35,
        "startTime": "2025-03-21T18:48:52",
        "records_since_previous": 2,
        "time_since_previous": "0:02:50"
    },
    {
        "crashpoint": 2654.88,
        "startTime": "2025-03-21T18:46:02",
        "records_since_previous": 1,
        "time_since_previous": "0:01:09"
    },
    {
        "crashpoint": 31.27,
        "startTime": "2025-03-21T18:44:53",
        "records_since_previous": 5,
        "time_since_previous": "0:02:46"
    },
    {
        "crashpoint": 54.67,
        "startTime": "2025-03-21T18:42:07",
        "records_since_previous": 12,
        "time_since_previous": "0:07:04"
    },
    {
        "crashpoint": 69.04,
        "startTime": "2025-03-21T18:35:03",
        "records_since_previous": 3,
        "time_since_previous": "0:02:14"
    },
    {
        "crashpoint": 122.03,
        "startTime": "2025-03-21T18:32:49",
        "records_since_previous": 28,
        "time_since_previous": "0:11:16"
    },
    {
        "crashpoint": 43.72,
        "startTime": "2025-03-21T18:21:33",
        "records_since_previous": 73,
        "time_since_previous": "0:30:54"
    },
    {
        "crashpoint": 54.41,
        "startTime": "2025-03-21T17:50:39",
        "records_since_previous": 19,
        "time_since_previous": "0:08:44"
    },
    {
        "crashpoint": 164.21,
        "startTime": "2025-03-21T17:41:55",
        "records_since_previous": 29,
        "time_since_previous": "0:12:51"
    },
    {
        "crashpoint": 37.26,
        "startTime": "2025-03-21T17:29:04",
        "records_since_previous": 38,
        "time_since_previous": "0:16:59"
    },
    {
        "crashpoint": 64.47,
        "startTime": "2025-03-21T17:12:05",
        "records_since_previous": 3,
        "time_since_previous": "0:01:55"
    },
    {
        "crashpoint": 52.76,
        "startTime": "2025-03-21T17:10:10",
        "records_since_previous": 1,
        "time_since_previous": "0:01:44"
    },
    {
        "crashpoint": 250.98,
        "startTime": "2025-03-21T17:08:26",
        "records_since_previous": 9,
        "time_since_previous": "0:04:35"
    },
    {
        "crashpoint": 32.04,
        "startTime": "2025-03-21T17:03:51",
        "records_since_previous": 27,
        "time_since_previous": "0:11:53"
    },
    {
        "crashpoint": 30.32,
        "startTime": "2025-03-21T16:51:58",
        "records_since_previous": 15,
        "time_since_previous": "0:07:13"
    },
    {
        "crashpoint": 36.8,
        "startTime": "2025-03-21T16:44:45",
        "records_since_previous": 29,
        "time_since_previous": "0:13:21"
    },
    {
        "crashpoint": 28.04,
        "startTime": "2025-03-21T16:31:24",
        "records_since_previous": 7,
        "time_since_previous": "0:04:25"
    },
    {
        "crashpoint": 30.0,
        "startTime": "2025-03-21T16:26:59",
        "records_since_previous": 20,
        "time_since_previous": "0:09:06"
    },
    {
        "crashpoint": 57.96,
        "startTime": "2025-03-21T16:17:53",
        "records_since_previous": 2,
        "time_since_previous": "0:02:46"
    },
    {
        "crashpoint": 1140.83,
        "startTime": "2025-03-21T16:15:07",
        "records_since_previous": 26,
        "time_since_previous": "0:11:35"
    },
    {
        "crashpoint": 34.63,
        "startTime": "2025-03-21T16:03:32",
        "records_since_previous": 39,
        "time_since_previous": "0:16:37"
    },
    {
        "crashpoint": 27.74,
        "startTime": "2025-03-21T15:46:55",
        "records_since_previous": 2,
        "time_since_previous": "0:01:15"
    },
    {
        "crashpoint": 20.08,
        "startTime": "2025-03-21T15:45:40",
        "records_since_previous": 99,
        "time_since_previous": "0:40:52"
    },
    {
        "crashpoint": 21.53,
        "startTime": "2025-03-21T15:04:48",
        "records_since_previous": 7,
        "time_since_previous": "0:03:08"
    },
    {
        "crashpoint": 20.91,
        "startTime": "2025-03-21T15:01:40",
        "records_since_previous": 42,
        "time_since_previous": "0:19:47"
    },
    {
        "crashpoint": 24.23,
        "startTime": "2025-03-21T14:41:53",
        "records_since_previous": 10,
        "time_since_previous": "0:04:46"
    },
    {
        "crashpoint": 24.16,
        "startTime": "2025-03-21T14:37:07",
        "records_since_previous": 5,
        "time_since_previous": "0:03:12"
    },
    {
        "crashpoint": 36.97,
        "startTime": "2025-03-21T14:33:55",
        "records_since_previous": 11,
        "time_since_previous": "0:05:31"
    },
    {
        "crashpoint": 39.46,
        "startTime": "2025-03-21T14:28:24",
        "records_since_previous": 37,
        "time_since_previous": "0:17:06"
    },
    {
        "crashpoint": 23.74,
        "startTime": "2025-03-21T14:11:18",
        "records_since_previous": 20,
        "time_since_previous": "0:09:06"
    },
    {
        "crashpoint": 27.21,
        "startTime": "2025-03-21T14:02:12",
        "records_since_previous": 57,
        "time_since_previous": "0:22:01"
    },
    {
        "crashpoint": 20.98,
        "startTime": "2025-03-21T13:40:11",
        "records_since_previous": 13,
        "time_since_previous": "0:06:50"
    },
    {
        "crashpoint": 23.06,
        "startTime": "2025-03-21T13:33:21",
        "records_since_previous": 27,
        "time_since_previous": "0:11:38"
    },
    {
        "crashpoint": 19.75,
        "startTime": "2025-03-21T13:21:43",
        "records_since_previous": 31,
        "time_since_previous": "0:12:48"
    },
    {
        "crashpoint": 58.11,
        "startTime": "2025-03-21T13:08:55",
        "records_since_previous": 5,
        "time_since_previous": "0:03:50"
    },
    {
        "crashpoint": 2529.07,
        "startTime": "2025-03-21T13:05:05",
        "records_since_previous": 176,
        "time_since_previous": "1:17:01"
    },
    {
        "crashpoint": 22.89,
        "startTime": "2025-03-21T11:48:04",
        "records_since_previous": 5,
        "time_since_previous": "0:02:35"
    },
    {
        "crashpoint": 53.89,
        "startTime": "2025-03-21T11:45:29",
        "records_since_previous": 1,
        "time_since_previous": "0:01:09"
    },
    {
        "crashpoint": 31.75,
        "startTime": "2025-03-21T11:44:20",
        "records_since_previous": 26,
        "time_since_previous": "0:12:19"
    },
    {
        "crashpoint": 22247.9,
        "startTime": "2025-03-21T11:32:01",
        "records_since_previous": 3,
        "time_since_previous": "0:02:23"
    },
    {
        "crashpoint": 134.49,
        "startTime": "2025-03-21T11:29:38",
        "records_since_previous": 4,
        "time_since_previous": "0:02:30"
    },
    {
        "crashpoint": 40.96,
        "startTime": "2025-03-21T11:27:08",
        "records_since_previous": 11,
        "time_since_previous": "0:05:52"
    },
    {
        "crashpoint": 50.75,
        "startTime": "2025-03-21T11:21:16",
        "records_since_previous": 2,
        "time_since_previous": "0:01:26"
    },
    {
        "crashpoint": 27.71,
        "startTime": "2025-03-21T11:19:50",
        "records_since_previous": 1,
        "time_since_previous": "0:01:09"
    },
    {
        "crashpoint": 31.88,
        "startTime": "2025-03-21T11:18:41",
        "records_since_previous": 87,
        "time_since_previous": "0:37:22"
    },
    {
        "crashpoint": 164.6,
        "startTime": "2025-03-21T10:41:19",
        "records_since_previous": 14,
        "time_since_previous": "0:08:21"
    },
    {
        "crashpoint": 19.78,
        "startTime": "2025-03-21T10:32:58",
        "records_since_previous": 39,
        "time_since_previous": "0:15:49"
    },
    {
        "crashpoint": 23.61,
        "startTime": "2025-03-21T10:17:09",
        "records_since_previous": 16,
        "time_since_previous": "0:07:05"
    },
    {
        "crashpoint": 171.72,
        "startTime": "2025-03-21T10:10:04",
        "records_since_previous": 8,
        "time_since_previous": "0:04:11"
    },
    {
        "crashpoint": 30.53,
        "startTime": "2025-03-21T10:05:53",
        "records_since_previous": 8,
        "time_since_previous": "0:04:05"
    },
    {
        "crashpoint": 19.38,
        "startTime": "2025-03-21T10:01:48",
        "records_since_previous": 6,
        "time_since_previous": "0:03:33"
    },
    {
        "crashpoint": 58.6,
        "startTime": "2025-03-21T09:58:15",
        "records_since_previous": 1,
        "time_since_previous": "0:02:14"
    },
    {
        "crashpoint": 1617.61,
        "startTime": "2025-03-21T09:56:01",
        "records_since_previous": 19,
        "time_since_previous": "0:08:23"
    },
    {
        "crashpoint": 128.13,
        "startTime": "2025-03-21T09:47:38",
        "records_since_previous": 4,
        "time_since_previous": "0:02:24"
    },
    {
        "crashpoint": 37.72,
        "startTime": "2025-03-21T09:45:14",
        "records_since_previous": 11,
        "time_since_previous": "0:06:25"
    },
    {
        "crashpoint": 22.55,
        "startTime": "2025-03-21T09:38:49",
        "records_since_previous": 8,
        "time_since_previous": "0:04:24"
    },
    {
        "crashpoint": 324.16,
        "startTime": "2025-03-21T09:34:25",
        "records_since_previous": 44,
        "time_since_previous": "0:19:53"
    },
    {
        "crashpoint": 26.4,
        "startTime": "2025-03-21T09:14:32",
        "records_since_previous": 2,
        "time_since_previous": "0:01:26"
    },
    {
        "crashpoint": 32.56,
        "startTime": "2025-03-21T09:13:06",
        "records_since_previous": 7,
        "time_since_previous": "0:03:41"
    },
    {
        "crashpoint": 28.01,
        "startTime": "2025-03-21T09:09:25",
        "records_since_previous": 6,
        "time_since_previous": "0:03:19"
    },
    {
        "crashpoint": 25.51,
        "startTime": "2025-03-21T09:06:06",
        "records_since_previous": 21,
        "time_since_previous": "0:08:57"
    },
    {
        "crashpoint": 20.7,
        "startTime": "2025-03-21T08:57:09",
        "records_since_previous": 2,
        "time_since_previous": "0:01:43"
    },
    {
        "crashpoint": 79.79,
        "startTime": "2025-03-21T08:55:26",
        "records_since_previous": 3,
        "time_since_previous": "0:01:53"
    },
    {
        "crashpoint": 33.7,
        "startTime": "2025-03-21T08:53:33",
        "records_since_previous": 20,
        "time_since_previous": "0:09:52"
    },
    {
        "crashpoint": 1273.01,
        "startTime": "2025-03-21T08:43:41",
        "records_since_previous": 6,
        "time_since_previous": "0:03:54"
    },
    {
        "crashpoint": 26.16,
        "startTime": "2025-03-21T08:39:47",
        "records_since_previous": 5,
        "time_since_previous": "0:03:42"
    },
    {
        "crashpoint": 40.04,
        "startTime": "2025-03-21T08:36:05",
        "records_since_previous": 51,
        "time_since_previous": "0:20:28"
    },
    {
        "crashpoint": 25.66,
        "startTime": "2025-03-21T08:15:37",
        "records_since_previous": 15,
        "time_since_previous": "0:05:32"
    },
    {
        "crashpoint": 19.63,
        "startTime": "2025-03-21T08:10:05",
        "records_since_previous": 13,
        "time_since_previous": "0:05:41"
    },
    {
        "crashpoint": 22.23,
        "startTime": "2025-03-21T08:04:24",
        "records_since_previous": 10,
        "time_since_previous": "0:04:50"
    },
    {
        "crashpoint": 43.27,
        "startTime": "2025-03-21T07:59:34",
        "records_since_previous": 32,
        "time_since_previous": "0:14:31"
    },
    {
        "crashpoint": 32.66,
        "startTime": "2025-03-21T07:45:03",
        "records_since_previous": 13,
        "time_since_previous": "0:06:06"
    },
    {
        "crashpoint": 33.43,
        "startTime": "2025-03-21T07:38:57",
        "records_since_previous": 49,
        "time_since_previous": "0:23:26"
    },
    {
        "crashpoint": 31.22,
        "startTime": "2025-03-21T07:15:31",
        "records_since_previous": 22,
        "time_since_previous": "0:09:40"
    },
    {
        "crashpoint": 94.01,
        "startTime": "2025-03-21T07:05:51",
        "records_since_previous": 9,
        "time_since_previous": "0:04:03"
    },
    {
        "crashpoint": 36.04,
        "startTime": "2025-03-21T07:01:48",
        "records_since_previous": 12,
        "time_since_previous": "0:06:34"
    },
    {
        "crashpoint": 313.9,
        "startTime": "2025-03-21T06:55:14",
        "records_since_previous": 23,
        "time_since_previous": "0:09:15"
    },
    {
        "crashpoint": 19.68,
        "startTime": "2025-03-21T06:45:59",
        "records_since_previous": 21,
        "time_since_previous": "0:09:19"
    },
    {
        "crashpoint": 61.96,
        "startTime": "2025-03-21T06:36:40",
        "records_since_previous": 41,
        "time_since_previous": "0:19:25"
    },
    {
        "crashpoint": 30.06,
        "startTime": "2025-03-21T06:17:15",
        "records_since_previous": 9,
        "time_since_previous": "0:04:47"
    },
    {
        "crashpoint": 25.16,
        "startTime": "2025-03-21T06:12:28",
        "records_since_previous": 10,
        "time_since_previous": "0:05:20"
    },
    {
        "crashpoint": 38.71,
        "startTime": "2025-03-21T06:07:08",
        "records_since_previous": 13,
        "time_since_previous": "0:06:12"
    },
    {
        "crashpoint": 106.86,
        "startTime": "2025-03-21T06:00:56",
        "records_since_previous": 39,
        "time_since_previous": "0:15:15"
    },
    {
        "crashpoint": 21.1,
        "startTime": "2025-03-21T05:45:41",
        "records_since_previous": 19,
        "time_since_previous": "0:09:57"
    },
    {
        "crashpoint": 218.87,
        "startTime": "2025-03-21T05:35:44",
        "records_since_previous": 28,
        "time_since_previous": "0:11:26"
    },
    {
        "crashpoint": 20.28,
        "startTime": "2025-03-21T05:24:18",
        "records_since_previous": 30,
        "time_since_previous": "0:13:35"
    },
    {
        "crashpoint": 36.02,
        "startTime": "2025-03-21T05:10:43",
        "records_since_previous": 5,
        "time_since_previous": "0:02:55"
    },
    {
        "crashpoint": 26.08,
        "startTime": "2025-03-21T05:07:48",
        "records_since_previous": 4,
        "time_since_previous": "0:02:22"
    },
    {
        "crashpoint": 26.45,
        "startTime": "2025-03-21T05:05:26",
        "records_since_previous": 50,
        "time_since_previous": "0:24:23"
    },
    {
        "crashpoint": 159.91,
        "startTime": "2025-03-21T04:41:03",
        "records_since_previous": 20,
        "time_since_previous": "0:08:36"
    },
    {
        "crashpoint": 58.27,
        "startTime": "2025-03-21T04:32:27",
        "records_since_previous": 8,
        "time_since_previous": "0:04:07"
    },
    {
        "crashpoint": 20.71,
        "startTime": "2025-03-21T04:28:20",
        "records_since_previous": 20,
        "time_since_previous": "0:08:55"
    },
    {
        "crashpoint": 27.29,
        "startTime": "2025-03-21T04:19:25",
        "records_since_previous": 11,
        "time_since_previous": "0:05:30"
    },
    {
        "crashpoint": 44.1,
        "startTime": "2025-03-21T04:13:55",
        "records_since_previous": 5,
        "time_since_previous": "0:02:48"
    },
    {
        "crashpoint": 27.19,
        "startTime": "2025-03-21T04:11:07",
        "records_since_previous": 31,
        "time_since_previous": "0:14:30"
    },
    {
        "crashpoint": 39.99,
        "startTime": "2025-03-21T03:56:37",
        "records_since_previous": 35,
        "time_since_previous": "0:18:12"
    },
    {
        "crashpoint": 75.58,
        "startTime": "2025-03-21T03:38:25",
        "records_since_previous": 10,
        "time_since_previous": "0:05:00"
    },
    {
        "crashpoint": 37.73,
        "startTime": "2025-03-21T03:33:25",
        "records_since_previous": 8,
        "time_since_previous": "0:04:38"
    },
    {
        "crashpoint": 26.01,
        "startTime": "2025-03-21T03:28:47",
        "records_since_previous": 22,
        "time_since_previous": "0:10:32"
    },
    {
        "crashpoint": 22.97,
        "startTime": "2025-03-21T03:18:15",
        "records_since_previous": 4,
        "time_since_previous": "0:02:56"
    },
    {
        "crashpoint": 37.44,
        "startTime": "2025-03-21T03:15:19",
        "records_since_previous": 95,
        "time_since_previous": "0:43:00"
    },
    {
        "crashpoint": 90.74,
        "startTime": "2025-03-21T02:32:19",
        "records_since_previous": 17,
        "time_since_previous": "0:06:40"
    },
    {
        "crashpoint": 19.1,
        "startTime": "2025-03-21T02:25:39",
        "records_since_previous": 7,
        "time_since_previous": "0:03:18"
    },
    {
        "crashpoint": 59.2,
        "startTime": "2025-03-21T02:22:21",
        "records_since_previous": 135,
        "time_since_previous": "0:57:57"
    },
    {
        "crashpoint": 48.13,
        "startTime": "2025-03-21T01:24:24",
        "records_since_previous": 28,
        "time_since_previous": "0:12:25"
    },
    {
        "crashpoint": 226.93,
        "startTime": "2025-03-21T01:11:59",
        "records_since_previous": 7,
        "time_since_previous": "0:02:54"
    },
    {
        "crashpoint": 19.41,
        "startTime": "2025-03-21T01:09:05",
        "records_since_previous": 15,
        "time_since_previous": "0:07:22"
    },
    {
        "crashpoint": 397.37,
        "startTime": "2025-03-21T01:01:43",
        "records_since_previous": 21,
        "time_since_previous": "0:09:57"
    },
    {
        "crashpoint": 360.47,
        "startTime": "2025-03-21T00:51:46",
        "records_since_previous": 18,
        "time_since_previous": "0:06:37"
    },
    {
        "crashpoint": 26.23,
        "startTime": "2025-03-21T00:45:09",
        "records_since_previous": 6,
        "time_since_previous": "0:03:30"
    },
    {
        "crashpoint": 36.19,
        "startTime": "2025-03-21T00:41:39",
        "records_since_previous": 20,
        "time_since_previous": "0:08:42"
    },
    {
        "crashpoint": 38.24,
        "startTime": "2025-03-21T00:32:57",
        "records_since_previous": 4,
        "time_since_previous": "0:02:18"
    },
    {
        "crashpoint": 28.14,
        "startTime": "2025-03-21T00:30:39",
        "records_since_previous": 24,
        "time_since_previous": "0:10:16"
    },
    {
        "crashpoint": 51.03,
        "startTime": "2025-03-21T00:20:23",
        "records_since_previous": 5,
        "time_since_previous": "0:02:24"
    },
    {
        "crashpoint": 32.19,
        "startTime": "2025-03-21T00:17:59",
        "records_since_previous": 36,
        "time_since_previous": "0:16:04"
    },
    {
        "crashpoint": 120.96,
        "startTime": "2025-03-21T00:01:55",
        "records_since_previous": 10,
        "time_since_previous": "0:04:45"
    },
    {
        "crashpoint": 44.43,
        "startTime": "2025-03-20T23:57:10",
        "records_since_previous": 40,
        "time_since_previous": "0:17:36"
    },
    {
        "crashpoint": 28.34,
        "startTime": "2025-03-20T23:39:34",
        "records_since_previous": 4,
        "time_since_previous": "0:02:05"
    },
    {
        "crashpoint": 20.0,
        "startTime": "2025-03-20T23:37:29",
        "records_since_previous": 11,
        "time_since_previous": "0:05:03"
    },
    {
        "crashpoint": 270.52,
        "startTime": "2025-03-20T23:32:26",
        "records_since_previous": 23,
        "time_since_previous": "0:10:27"
    },
    {
        "crashpoint": 81.64,
        "startTime": "2025-03-20T23:21:59",
        "records_since_previous": 5,
        "time_since_previous": "0:03:13"
    },
    {
        "crashpoint": 58.75,
        "startTime": "2025-03-20T23:18:46",
        "records_since_previous": 13,
        "time_since_previous": "0:07:00"
    },
    {
        "crashpoint": 40.98,
        "startTime": "2025-03-20T23:11:46",
        "records_since_previous": 24,
        "time_since_previous": "0:10:10"
    },
    {
        "crashpoint": 24.06,
        "startTime": "2025-03-20T23:01:36",
        "records_since_previous": 9,
        "time_since_previous": "0:04:10"
    },
    {
        "crashpoint": 25.24,
        "startTime": "2025-03-20T22:57:26",
        "records_since_previous": 15,
        "time_since_previous": "0:06:02"
    },
    {
        "crashpoint": 44.97,
        "startTime": "2025-03-20T22:51:24",
        "records_since_previous": 9,
        "time_since_previous": "0:04:19"
    },
    {
        "crashpoint": 31.54,
        "startTime": "2025-03-20T22:47:05",
        "records_since_previous": 17,
        "time_since_previous": "0:08:39"
    },
    {
        "crashpoint": 48.79,
        "startTime": "2025-03-20T22:38:26",
        "records_since_previous": 42,
        "time_since_previous": "0:19:08"
    },
    {
        "crashpoint": 77.48,
        "startTime": "2025-03-20T22:19:18",
        "records_since_previous": 11,
        "time_since_previous": "0:04:26"
    },
    {
        "crashpoint": 23.26,
        "startTime": "2025-03-20T22:14:52",
        "records_since_previous": 20,
        "time_since_previous": "0:07:38"
    },
    {
        "crashpoint": 36.66,
        "startTime": "2025-03-20T22:07:14",
        "records_since_previous": 7,
        "time_since_previous": "0:03:31"
    },
    {
        "crashpoint": 20.47,
        "startTime": "2025-03-20T22:03:43",
        "records_since_previous": 19,
        "time_since_previous": "0:09:37"
    },
    {
        "crashpoint": 27.29,
        "startTime": "2025-03-20T21:54:06",
        "records_since_previous": 11,
        "time_since_previous": "0:06:16"
    },
    {
        "crashpoint": 30.12,
        "startTime": "2025-03-20T21:47:50",
        "records_since_previous": 17,
        "time_since_previous": "0:06:48"
    },
    {
        "crashpoint": 82.28,
        "startTime": "2025-03-20T21:41:02",
        "records_since_previous": 23,
        "time_since_previous": "0:10:34"
    },
    {
        "crashpoint": 22.23,
        "startTime": "2025-03-20T21:30:28",
        "records_since_previous": 44,
        "time_since_previous": "0:18:57"
    },
    {
        "crashpoint": 60.08,
        "startTime": "2025-03-20T21:11:31",
        "records_since_previous": 7,
        "time_since_previous": "0:03:38"
    },
    {
        "crashpoint": 24.35,
        "startTime": "2025-03-20T21:07:53",
        "records_since_previous": 3,
        "time_since_previous": "0:02:16"
    },
    {
        "crashpoint": 43.79,
        "startTime": "2025-03-20T21:05:37",
        "records_since_previous": 23,
        "time_since_previous": "0:09:19"
    },
    {
        "crashpoint": 22.66,
        "startTime": "2025-03-20T20:56:18",
        "records_since_previous": 35,
        "time_since_previous": "0:15:03"
    },
    {
        "crashpoint": 73.39,
        "startTime": "2025-03-20T20:41:15",
        "records_since_previous": 45,
        "time_since_previous": "0:16:46"
    },
    {
        "crashpoint": 20.81,
        "startTime": "2025-03-20T20:24:29",
        "records_since_previous": 45,
        "time_since_previous": "0:19:32"
    },
    {
        "crashpoint": 36.85,
        "startTime": "2025-03-20T20:04:57",
        "records_since_previous": 32,
        "time_since_previous": "0:17:26"
    },
    {
        "crashpoint": 3898.13,
        "startTime": "2025-03-20T19:47:31",
        "records_since_previous": 55,
        "time_since_previous": "0:24:57"
    },
    {
        "crashpoint": 33.93,
        "startTime": "2025-03-20T19:22:34",
        "records_since_previous": 7,
        "time_since_previous": "0:04:13"
    },
    {
        "crashpoint": 103.09,
        "startTime": "2025-03-20T19:18:21",
        "records_since_previous": 2,
        "time_since_previous": "0:01:19"
    },
    {
        "crashpoint": 26.66,
        "startTime": "2025-03-20T19:17:02",
        "records_since_previous": 2,
        "time_since_previous": "0:01:33"
    },
    {
        "crashpoint": 35.88,
        "startTime": "2025-03-20T19:15:29",
        "records_since_previous": 31,
        "time_since_previous": "0:15:49"
    },
    {
        "crashpoint": 27.81,
        "startTime": "2025-03-20T18:59:40",
        "records_since_previous": 19,
        "time_since_previous": "0:11:23"
    },
    {
        "crashpoint": 1655.84,
        "startTime": "2025-03-20T18:48:17",
        "records_since_previous": 13,
        "time_since_previous": "0:06:09"
    },
    {
        "crashpoint": 24.02,
        "startTime": "2025-03-20T18:42:08",
        "records_since_previous": 45,
        "time_since_previous": "0:19:57"
    },
    {
        "crashpoint": 76.17,
        "startTime": "2025-03-20T18:22:11",
        "records_since_previous": 19,
        "time_since_previous": "0:09:39"
    },
    {
        "crashpoint": 20.32,
        "startTime": "2025-03-20T18:12:32",
        "records_since_previous": 22,
        "time_since_previous": "0:10:27"
    },
    {
        "crashpoint": 70.83,
        "startTime": "2025-03-20T18:02:05",
        "records_since_previous": 54,
        "time_since_previous": "0:25:35"
    },
    {
        "crashpoint": 231.82,
        "startTime": "2025-03-20T17:36:30",
        "records_since_previous": 9,
        "time_since_previous": "0:03:58"
    },
    {
        "crashpoint": 22.83,
        "startTime": "2025-03-20T17:32:32",
        "records_since_previous": 2,
        "time_since_previous": "0:01:30"
    },
    {
        "crashpoint": 41.32,
        "startTime": "2025-03-20T17:31:02",
        "records_since_previous": 25,
        "time_since_previous": "0:11:26"
    },
    {
        "crashpoint": 22.56,
        "startTime": "2025-03-20T17:19:36",
        "records_since_previous": 27,
        "time_since_previous": "0:13:03"
    },
    {
        "crashpoint": 52.71,
        "startTime": "2025-03-20T17:06:33",
        "records_since_previous": 16,
        "time_since_previous": "0:06:16"
    },
    {
        "crashpoint": 66.08,
        "startTime": "2025-03-20T17:00:17",
        "records_since_previous": 25,
        "time_since_previous": "0:09:41"
    },
    {
        "crashpoint": 29.32,
        "startTime": "2025-03-20T16:50:36",
        "records_since_previous": 14,
        "time_since_previous": "0:08:16"
    },
    {
        "crashpoint": 42.95,
        "startTime": "2025-03-20T16:42:20",
        "records_since_previous": 6,
        "time_since_previous": "0:03:41"
    },
    {
        "crashpoint": 25.58,
        "startTime": "2025-03-20T16:38:39",
        "records_since_previous": 2,
        "time_since_previous": "0:01:41"
    },
    {
        "crashpoint": 90.1,
        "startTime": "2025-03-20T16:36:58",
        "records_since_previous": 3,
        "time_since_previous": "0:02:34"
    },
    {
        "crashpoint": 37.46,
        "startTime": "2025-03-20T16:34:24",
        "records_since_previous": 17,
        "time_since_previous": "0:09:16"
    },
    {
        "crashpoint": 71.53,
        "startTime": "2025-03-20T16:25:08",
        "records_since_previous": 43,
        "time_since_previous": "0:21:15"
    },
    {
        "crashpoint": 84.07,
        "startTime": "2025-03-20T16:03:53",
        "records_since_previous": 5,
        "time_since_previous": "0:02:34"
    },
    {
        "crashpoint": 46.83,
        "startTime": "2025-03-20T16:01:19",
        "records_since_previous": 72,
        "time_since_previous": "0:29:21"
    },
    {
        "crashpoint": 102.16,
        "startTime": "2025-03-20T15:31:58",
        "records_since_previous": 5,
        "time_since_previous": "0:02:37"
    },
    {
        "crashpoint": 19.5,
        "startTime": "2025-03-20T15:29:21",
        "records_since_previous": 1,
        "time_since_previous": "0:01:16"
    },
    {
        "crashpoint": 48.37,
        "startTime": "2025-03-20T15:28:05",
        "records_since_previous": 12,
        "time_since_previous": "0:06:13"
    },
    {
        "crashpoint": 20.38,
        "startTime": "2025-03-20T15:21:52",
        "records_since_previous": 3,
        "time_since_previous": "0:02:22"
    },
    {
        "crashpoint": 58.89,
        "startTime": "2025-03-20T15:19:30",
        "records_since_previous": 14,
        "time_since_previous": "0:07:20"
    },
    {
        "crashpoint": 39.38,
        "startTime": "2025-03-20T15:12:10",
        "records_since_previous": 25,
        "time_since_previous": "0:11:41"
    },
    {
        "crashpoint": 94.77,
        "startTime": "2025-03-20T15:00:29",
        "records_since_previous": 11,
        "time_since_previous": "0:06:05"
    },
    {
        "crashpoint": 40.87,
        "startTime": "2025-03-20T14:54:24",
        "records_since_previous": 23,
        "time_since_previous": "0:10:30"
    },
    {
        "crashpoint": 78.67,
        "startTime": "2025-03-20T14:43:54",
        "records_since_previous": 54,
        "time_since_previous": "0:26:12"
    },
    {
        "crashpoint": 24.66,
        "startTime": "2025-03-20T14:17:42",
        "records_since_previous": 1,
        "time_since_previous": "0:01:08"
    }
]