[
    {
        "crashpoint": 128615.17,
        "startTime": "2025-02-11T09:39:40",
        "records_since_previous": 43574,
        "time_since_previous": "14 days, 3:10:14"
    },
    {
        "crashpoint": 50079.71,
        "startTime": "2025-01-28T06:29:26",
        "records_since_previous": 13513,
        "time_since_previous": "4 days, 9:20:49"
    },
    {
        "crashpoint": 164138.88,
        "startTime": "2025-01-23T21:08:37",
        "records_since_previous": 27862,
        "time_since_previous": "9 days, 2:00:21"
    },
    {
        "crashpoint": 50915.05,
        "startTime": "2025-01-14T19:08:16",
        "records_since_previous": 200154,
        "time_since_previous": "65 days, 16:09:04"
    },
    {
        "crashpoint": 154996.45,
        "startTime": "2024-11-10T02:59:12",
        "records_since_previous": 123075,
        "time_since_previous": "40 days, 0:13:55"
    },
    {
        "crashpoint": 55567.4,
        "startTime": "2024-10-01T02:45:17",
        "records_since_previous": 0,
        "time_since_previous": "40 days, 0:13:55"
    }
]